finalysis/__init__.py
finalysis/__init__.pyi
finalysis/util.py
finalysis/instruments/__init__.py
finalysis/instruments/__init__.pyi
finalysis/instruments/base.py
finalysis/instruments/instruments.py
finalysis/plot/__init__.py
finalysis/plot/plot.py
finalysis-0.1.9.dist-info/METADATA
finalysis-0.1.9.dist-info/WHEEL
finalysis-0.1.9.dist-info/top_level.txt
finalysis-0.1.9.dist-info/RECORD
