Metadata-Version: 2.4
Name: finalysis
Version: 0.1.9
Summary: A python library for financial instrument payoff analysis
Author-email: Marcel Claramunt <marcel@marcelc.uk>
Project-URL: repo, https://github.com/tribulnation/finalysis.git
Requires-Python: >=3.10
Requires-Dist: numpy
Requires-Dist: scipy
Requires-Dist: typing-extensions
Requires-Dist: lazy-loader
Requires-Dist: plotly
Requires-Dist: nbformat
